{
  "products": [
    {
      "id": 1,
      "type": "Expense",
      "description": "This is the first product.",
      "price": 19.99,
      "category": "Food & Drinks",
      "date": "2023-09-08"
    },
    {
      "id": 2,
      "type": "Income",
      "description": "This is the second product.",
      "price": 29.99,
      "category": "Salary",
      "date": "2023-09-09"
    },
    {
      "id": 3,
      "type": "Expense",
      "description": "This is the third product.",
      "price": 39.99,
      "category": "Housing",
      "date": "2023-09-10"
    }
  ]
}